<?xml version="1.0" encoding="UTF-8" standalone="no"?>
<Configuration version="2.0.0.12">
  <DisplayManager>
    <SystemInitScript dnOrder="0"/>
    <SystemStartScript dnOrder="1"/>
  </DisplayManager>
  <General>
    <Board dnOrder="0" name=""/>
    <ForceOptimization dnOrder="1" flag="true"/>
    <HarmonyPath dnOrder="2" path="../../../.."/>
    <MergeStrategy dnOrder="3" flag="ALL"/>
    <Processor dnOrder="4" name="PIC32MX695F512L"/>
  </General>
  <Manifest>
    <CompilerItems dnOrder="0">
      <C32 dnOrder="0">
        <Include dnOrder="0" value="C:\microchip\harmony\usb\apps\usb\device\cdc_com_port_single\firmware\src"/>
        <Include dnOrder="1" value="C:\microchip\harmony\usb\apps\usb\device\cdc_com_port_single\firmware\src\system_config\chipkit_wf32"/>
        <Include dnOrder="2" value="C:\microchip\harmony\usb\framework"/>
        <Include dnOrder="3" value="C:\microchip\harmony\usb\apps\usb\device\cdc_com_port_single\firmware\src\system_config\chipkit_wf32\framework"/>
        <Include dnOrder="4" value="../src/system_config/chipkit_wf32/bsp"/>
      </C32>
    </CompilerItems>
    <Files dnOrder="1">
      <File dnOrder="0">
        <Name dnOrder="0">drv_usbfs_local.h</Name>
        <Path dnOrder="1">Header Files/framework/driver/usb/usbfs/src</Path>
      </File>
      <File dnOrder="1">
        <Name dnOrder="0">driver_common.h</Name>
        <Path dnOrder="1">Header Files/framework/driver</Path>
      </File>
      <File dnOrder="2">
        <Name dnOrder="0">drv_usbhs.h</Name>
        <Path dnOrder="1">Header Files/framework/driver/usb/usbhs</Path>
      </File>
      <File dnOrder="3">
        <Name dnOrder="0">drv_usbfs_static.h</Name>
        <Path dnOrder="1">Header Files/framework/driver/usb/usbfs</Path>
      </File>
      <File dnOrder="4">
        <Name dnOrder="0">usb_device_local.h</Name>
        <Path dnOrder="1">Header Files/framework/usb/src</Path>
      </File>
      <File dnOrder="5">
        <Name dnOrder="0">usb_chapter_9.h</Name>
        <Path dnOrder="1">Header Files/framework/usb</Path>
      </File>
      <File dnOrder="6">
        <Name dnOrder="0">driver.h</Name>
        <Path dnOrder="1">Header Files/framework/driver</Path>
      </File>
      <File dnOrder="7">
        <Name dnOrder="0">sys_int_pic32.c</Name>
        <Path dnOrder="1">Source Files/framework/system/int/src</Path>
      </File>
      <File dnOrder="8">
        <Name dnOrder="0">usb_device.c</Name>
        <Path dnOrder="1">Source Files/framework/usb/src/dynamic</Path>
      </File>
      <File dnOrder="9">
        <Name dnOrder="0">sys_clk.h</Name>
        <Path dnOrder="1">Header Files/framework/system/clk</Path>
      </File>
      <File dnOrder="10">
        <Name dnOrder="0">usb_device.h</Name>
        <Path dnOrder="1">Header Files/framework/usb</Path>
      </File>
      <File dnOrder="11">
        <Name dnOrder="0">sys_int_private.h</Name>
        <Path dnOrder="1">Header Files/framework/system/int/src</Path>
      </File>
      <File dnOrder="12">
        <Name dnOrder="0">system.h</Name>
        <Path dnOrder="1">Header Files/framework/system</Path>
      </File>
      <File dnOrder="13">
        <Name dnOrder="0">usb_cdc.h</Name>
        <Path dnOrder="1">Header Files/framework/usb</Path>
      </File>
      <File dnOrder="14">
        <Name dnOrder="0">drv_usbfs.h</Name>
        <Path dnOrder="1">Header Files/framework/driver/usb/usbfs</Path>
      </File>
      <File dnOrder="15">
        <Name dnOrder="0">usb_device_cdc_local.h</Name>
        <Path dnOrder="1">Header Files/framework/usb/src</Path>
      </File>
      <File dnOrder="16">
        <Name dnOrder="0">sys_int.h</Name>
        <Path dnOrder="1">Header Files/framework/system/int</Path>
      </File>
      <File dnOrder="17">
        <Name dnOrder="0">drv_usb.h</Name>
        <Path dnOrder="1">Header Files/framework/driver/usb</Path>
      </File>
      <File dnOrder="18">
        <Name dnOrder="0">osal_impl_basic.h</Name>
        <Path dnOrder="1">Header Files/framework/osal/src</Path>
      </File>
      <File dnOrder="19">
        <Name dnOrder="0">usb_billboard.h</Name>
        <Path dnOrder="1">Header Files/framework/usb</Path>
      </File>
      <File dnOrder="20">
        <Name dnOrder="0">drv_usbfs.c</Name>
        <Path dnOrder="1">Source Files/framework/driver/usb/usbfs/src/dynamic</Path>
      </File>
      <File dnOrder="21">
        <Name dnOrder="0">sys_devcon.c</Name>
        <Path dnOrder="1">Source Files/framework/system/devcon/src</Path>
      </File>
      <File dnOrder="22">
        <Name dnOrder="0">usb_host.h</Name>
        <Path dnOrder="1">Header Files/framework/usb</Path>
      </File>
      <File dnOrder="23">
        <Name dnOrder="0">osal.h</Name>
        <Path dnOrder="1">Header Files/framework/osal</Path>
      </File>
      <File dnOrder="24">
        <Name dnOrder="0">usb_device_cdc.h</Name>
        <Path dnOrder="1">Header Files/framework/usb</Path>
      </File>
      <File dnOrder="25">
        <Name dnOrder="0">usb_host_hub_interface.h</Name>
        <Path dnOrder="1">Header Files/framework/usb</Path>
      </File>
      <File dnOrder="26">
        <Name dnOrder="0">usb_common.h</Name>
        <Path dnOrder="1">Header Files/framework/usb</Path>
      </File>
      <File dnOrder="27">
        <Name dnOrder="0">sys_ports.h</Name>
        <Path dnOrder="1">Header Files/framework/system/ports</Path>
      </File>
      <File dnOrder="28">
        <Name dnOrder="0">usb_hub.h</Name>
        <Path dnOrder="1">Header Files/framework/usb</Path>
      </File>
      <File dnOrder="29">
        <Name dnOrder="0">sys_common.h</Name>
        <Path dnOrder="1">Header Files/framework/system/common</Path>
      </File>
      <File dnOrder="30">
        <Name dnOrder="0">sys_buffer.h</Name>
        <Path dnOrder="1">Header Files/framework/system/common</Path>
      </File>
      <File dnOrder="31">
        <Name dnOrder="0">usb_device_mapping.h</Name>
        <Path dnOrder="1">Header Files/framework/usb/src</Path>
      </File>
      <File dnOrder="32">
        <Name dnOrder="0">usb_host_hub.h</Name>
        <Path dnOrder="1">Header Files/framework/usb</Path>
      </File>
      <File dnOrder="33">
        <Name dnOrder="0">sys_clk_compatibility.h</Name>
        <Path dnOrder="1">Header Files/framework/system/clk</Path>
      </File>
      <File dnOrder="34">
        <Name dnOrder="0">osal_impl_none.h</Name>
        <Path dnOrder="1">Header Files/framework/osal/src</Path>
      </File>
      <File dnOrder="35">
        <Name dnOrder="0">sys_clk_mapping.h</Name>
        <Path dnOrder="1">Header Files/framework/system/clk</Path>
      </File>
      <File dnOrder="36">
        <Name dnOrder="0">osal_definitions.h</Name>
        <Path dnOrder="1">Header Files/framework/osal</Path>
      </File>
      <File dnOrder="37">
        <Name dnOrder="0">sys_int_mapping.h</Name>
        <Path dnOrder="1">Header Files/framework/system/int</Path>
      </File>
      <File dnOrder="38">
        <Name dnOrder="0">sys_devcon.h</Name>
        <Path dnOrder="1">Header Files/framework/system/devcon</Path>
      </File>
      <File dnOrder="39">
        <Name dnOrder="0">drv_usbfs_device.c</Name>
        <Path dnOrder="1">Source Files/framework/driver/usb/usbfs/src/dynamic</Path>
      </File>
      <File dnOrder="40">
        <Name dnOrder="0">sys_debug.h</Name>
        <Path dnOrder="1">Header Files/framework/system/debug</Path>
      </File>
      <File dnOrder="41">
        <Name dnOrder="0">usb_device_cdc_acm.c</Name>
        <Path dnOrder="1">Source Files/framework/usb/src/dynamic</Path>
      </File>
      <File dnOrder="42">
        <Name dnOrder="0">sys_module.h</Name>
        <Path dnOrder="1">Header Files/framework/system/common</Path>
      </File>
      <File dnOrder="43">
        <Name dnOrder="0">sys_devcon_pic32mx.c</Name>
        <Path dnOrder="1">Source Files/framework/system/devcon/src</Path>
      </File>
      <File dnOrder="44">
        <Name dnOrder="0">sys_devcon_local.h</Name>
        <Path dnOrder="1">Header Files/framework/system/devcon/src</Path>
      </File>
      <File dnOrder="45">
        <Name dnOrder="0">drv_usbfs_variant_mapping.h</Name>
        <Path dnOrder="1">Header Files/framework/driver/usb/usbfs/src</Path>
      </File>
      <File dnOrder="46">
        <Name dnOrder="0">sys_queue.h</Name>
        <Path dnOrder="1">Header Files/framework/system/common</Path>
      </File>
      <File dnOrder="47">
        <Name dnOrder="0">usb_device_cdc.c</Name>
        <Path dnOrder="1">Source Files/framework/usb/src/dynamic</Path>
      </File>
      <File dnOrder="48">
        <Name dnOrder="0">drv_usbfs_mapping.h</Name>
        <Path dnOrder="1">Header Files/framework/driver/usb/usbfs</Path>
      </File>
      <File dnOrder="49">
        <Name dnOrder="0">usb_host_client_driver.h</Name>
        <Path dnOrder="1">Header Files/framework/usb</Path>
      </File>
    </Files>
    <Libraries dnOrder="2">
      <Library dnOrder="0" value="../../../../../../bin/framework/peripheral/PIC32MX695F512L_peripherals.a"/>
    </Libraries>
    <Templates dnOrder="3">
      <Template dnOrder="0">
        <Name dnOrder="0">main.c</Name>
        <Path dnOrder="1">Source Files/app</Path>
      </Template>
      <Template dnOrder="1">
        <Checksum dnOrder="0">83E28A9509BFB1178054925FE7ED2D75</Checksum>
        <Name dnOrder="1">sys_ports_static.c</Name>
        <Path dnOrder="2">Source Files/app/system_config/chipkit_wf32/framework/system/ports/src</Path>
        <ProjectFileChecksum dnOrder="3">57E6670CF29B387333F1DB4C89F28EB6</ProjectFileChecksum>
      </Template>
      <Template dnOrder="2">
        <Checksum dnOrder="0">4A576F3E2B6EED0F575746594ADE0082</Checksum>
        <Name dnOrder="1">bsp.c</Name>
        <Path dnOrder="2">Source Files/app/system_config/chipkit_wf32/bsp</Path>
        <ProjectFileChecksum dnOrder="3">5E8DFE3557F1E86E78280C82FE535152</ProjectFileChecksum>
      </Template>
      <Template dnOrder="3">
        <Name dnOrder="0">app.c</Name>
        <Path dnOrder="1">Source Files/app</Path>
      </Template>
      <Template dnOrder="4">
        <Checksum dnOrder="0">26C534E11FCF0F431B6C24CD3BE7FC10</Checksum>
        <Name dnOrder="1">system_init.c</Name>
        <Path dnOrder="2">Source Files/app/system_config/chipkit_wf32</Path>
        <ProjectFileChecksum dnOrder="3">18F67156BD04B97057FF6BA7F56A61F0</ProjectFileChecksum>
      </Template>
      <Template dnOrder="5">
        <Checksum dnOrder="0">61C11F06F103735D7B3984C54A722725</Checksum>
        <Name dnOrder="1">system_interrupt.c</Name>
        <Path dnOrder="2">Source Files/app/system_config/chipkit_wf32</Path>
        <ProjectFileChecksum dnOrder="3">A5062F6208678B3A2643A180BD853F6A</ProjectFileChecksum>
      </Template>
      <Template dnOrder="6">
        <Checksum dnOrder="0">20E92807B76CBF42C1CACC2BCCB8A6DA</Checksum>
        <Name dnOrder="1">bsp.h</Name>
        <Path dnOrder="2">Header Files/app/system_config/chipkit_wf32/bsp</Path>
        <ProjectFileChecksum dnOrder="3">55352FC65C45682652E683D707885743</ProjectFileChecksum>
      </Template>
      <Template dnOrder="7">
        <Checksum dnOrder="0">C111969CA43D6CEA1E9E33A6164E7AE0</Checksum>
        <Name dnOrder="1">system_exceptions.c</Name>
        <Path dnOrder="2">Source Files/app/system_config/chipkit_wf32</Path>
        <ProjectFileChecksum dnOrder="3">B1628C9614D46F700A9125EC2A5CA1FA</ProjectFileChecksum>
      </Template>
      <Template dnOrder="8">
        <Checksum dnOrder="0">1FC7D92DDB9E3B50C1EF72A293B0DDF2</Checksum>
        <Name dnOrder="1">system_definitions.h</Name>
        <Path dnOrder="2">Header Files/app/system_config/chipkit_wf32</Path>
        <ProjectFileChecksum dnOrder="3">907BC6B5D5C4E760405573B9096CF3DC</ProjectFileChecksum>
      </Template>
      <Template dnOrder="9">
        <Name dnOrder="0">app.h</Name>
        <Path dnOrder="1">Header Files/app</Path>
      </Template>
      <Template dnOrder="10">
        <Checksum dnOrder="0">8A55B10A2A7732C58D888F22D5E7EE1B</Checksum>
        <Name dnOrder="1">system_config.h</Name>
        <Path dnOrder="2">Header Files/app/system_config/chipkit_wf32</Path>
        <ProjectFileChecksum dnOrder="3">7EF7A4CF9EDEC4C2226B17A6D74A011A</ProjectFileChecksum>
      </Template>
      <Template dnOrder="11">
        <Checksum dnOrder="0">FDF6C8068CFFAEEC5F8537A8D6514230</Checksum>
        <Name dnOrder="1">sys_clk_static.c</Name>
        <Path dnOrder="2">Source Files/app/system_config/chipkit_wf32/framework/system/clk/src</Path>
        <ProjectFileChecksum dnOrder="3">E519060CA61DBE819A8964EC36595056</ProjectFileChecksum>
      </Template>
      <Template dnOrder="12">
        <Checksum dnOrder="0">C051440866B3433982D20908212CADC7</Checksum>
        <Name dnOrder="1">system_tasks.c</Name>
        <Path dnOrder="2">Source Files/app/system_config/chipkit_wf32</Path>
        <ProjectFileChecksum dnOrder="3">3EDD250052254E186E820FCA8FA575D1</ProjectFileChecksum>
      </Template>
    </Templates>
  </Manifest>
</Configuration>
